plymouth_bdft/__init__.py
plymouth_bdft/conductivity.py
plymouth_bdft/genesis.py
plymouth_bdft/immutiblenamespace.py
plymouth_bdft/plotting_utils.py
plymouth_bdft/tbm_dft.py
plymouth_bdft-0.3.3.dist-info/METADATA
plymouth_bdft-0.3.3.dist-info/WHEEL
plymouth_bdft-0.3.3.dist-info/top_level.txt
plymouth_bdft-0.3.3.dist-info/RECORD
